{
  "Code": 0,
  "Message": "success",
  "Data": {
    "HasMore": false,
    "SearchHashId": "e562dd6fc9046d70fd68e1b2ddb22fe2",
    "Items": [
      {
        "Title": "买电车是买纯电还是混动? - 知乎",
        "ContentType": "Answer",
        "ContentID": "-4225118215512023279",
        "ContentText": "这个问题得结合你自身的条件和使用场景来看。\n如果你自己家里有条件安装充电桩，主要的使用场景是市内代步加上周边短途游，很少有长途用车，尤其是节假日长途用车需求，那可以毫不犹豫的买纯电车。\n少了一套发动机、变速箱和油箱这些负重，你得到的是更长的纯电续航里程和更低的使用维护成本。\n如果你家里没有安装充电桩的条件，平常使用公用充电桩也比较困难，但是平常基本上也不怎么跑长途，也可以优先考虑买纯电车，现在的纯电车续航基本都可以做到600km以上，实际使用跑个400km完全没问题，即使按每天50km的通勤距离算，周末专门去充个电也足够了。\n如果家里有条件安装充电桩，但是平常有比较多的长途需求，主要用车是在一二线城市，可以优先考虑蔚来的换电，蔚来的换电网络已经非常发达了，节假日在高速上也不怕充电排队。",
        "Url": "https://www.zhihu.com/question/2055137401157296841/answer/2055355174231741963?utm_medium=openapi_platform&utm_source=124a2a56",
        "CommentCount": 0,
        "VoteUpCount": 1,
        "AuthorName": "拨片换挡",
        "AuthorAvatar": "https://picx.zhimg.com/50/v2-1ca400fca4b51397589ccef57339f4e6_l.jpg?source=bbf6831d",
        "AuthorBadge": "",
        "AuthorBadgeText": "",
        "EditTime": 1782814860,
        "AuthorityLevel": "1",
        "RankingScore": 1.8789264
      },
      {
        "Title": "买电车是买纯电还是混动? - 知乎",
        "ContentType": "Answer",
        "ContentID": "3288982093042063599",
        "ContentText": "有长途需求么？\n如果很少有长途需求，大多上班通勤，我的建议是买纯电。\n因为真正买了车之后，纯电跑和加油跑区别一下子就出来了，绝大多数人都会想要省点钱，用电跑的时候占多数情况。\n而混动车的纯电续航比较低，我一个朋友，她当初买车就是买的混动，日常上下班通勤四五十公里，而她混动的电续航只有70，所以她几乎每天都在充电。\n没错，就是每天用随车充充电，一充充一晚上。\n用油么？还是用的，但一年下来用油很少。加上前一两个月油价飞涨，她就更不舍得用油跑了，真的有点麻烦。\n我最后买了纯电车，日常上下班接送孩子，一天来回四十公里，开一两周才充一次电，就不会觉得那么麻烦。\n而且短途出行，去市里来回200公里，定速100跑，回家后还能剩十来个电，也是能满足我的需求的。",
        "Url": "https://www.zhihu.com/question/2055137401157296841/answer/2055937447863891139?utm_medium=openapi_platform&utm_source=124a2a56",
        "CommentCount": 0,
        "VoteUpCount": 1,
        "AuthorName": "大胆妈妈爱攒钱",
        "AuthorAvatar": "https://pic1.zhimg.com/50/v2-6375dbccb2671a425c2e81cc594b8872_l.jpg?source=bbf6831d",
        "AuthorBadge": "https://picx.zhimg.com/v2-2ddc5cc683982648f6f123616fb4ec09_l.png?source=32738c0c",
        "AuthorBadgeText": "教师资格证持证人",
        "EditTime": 1782953685,
        "AuthorityLevel": "1",
        "RankingScore": 1.7834724
      },
      {
        "Title": "买电车是买纯电还是混动? - 知乎",
        "ContentType": "Answer",
        "ContentID": "-2929965161998531391",
        "ContentText": "纯电车用户路过，先给我的结论：\n如果你想要购买的级别的车型，能够提供 700+的 CLTC 续航，那必然买纯电。如果你想要买三排七座车型，那大部分产品都是混动或增程，这个尺寸的车很难做纯电长续航。\n如果是纯城市代步小车，例如吉利星愿这种，那也没有必要，同时也没有混动产品，上了混动反而损失了这类小车的经济性。\n如果是大型 SUV 例如极氪 9x，那最好舍得用油，才能有 100% 的用车体验。\n通常买了混动（包括增程，插混）的后，你会发现：你舍不得用油，在短途旅行就是当纯电用，发动机或者增程器更多购买的不是续航，而是安全感。\n那纯电车有没有补能焦虑呢？\n如果你能满足 CLTC 700+，电池支持 3C 以上快充，那无论是否有家充条件，纯电车都不会给你有续航的焦虑，甚至充电是一个低频的事情。",
        "Url": "https://www.zhihu.com/question/2055137401157296841/answer/2055265535076701734?utm_medium=openapi_platform&utm_source=124a2a56",
        "CommentCount": 2,
        "VoteUpCount": 2,
        "AuthorName": "YeahGo",
        "AuthorAvatar": "https://picx.zhimg.com/50/v2-c2c6c646760f5fd72828834712b7c5e0_l.jpg?source=bbf6831d",
        "AuthorBadge": "",
        "AuthorBadgeText": "",
        "EditTime": 1782794100,
        "CommentInfoList": [
          {
            "Content": "所以说大唐杀死了比赛"
          }
        ],
        "AuthorityLevel": "1",
        "RankingScore": 1.7150828
      },
      {
        "Title": "买新能源车,是买纯电的呢还是那种油电混合的,城里上下班用,选那种比较好? - 知乎",
        "ContentType": "Answer",
        "ContentID": "6288531199303270734",
        "ContentText": "我个人是混动乘用车用户，以我的经验来看，混动是当前大环境下更好的出行产品实现。当然，对于提问者的使用需求和其所处的环境不确定，所以有几个前提：\n1 如果你所在城市对于新能源车用车的政策不鼓励混动、鼓励纯电，那么优选纯电；（上海是这种情况，如果你没有蓝牌，购买混动意味着要竞拍蓝牌（大牌）先，没有免费绿牌优惠政策）\n2 如果你拥有便利/固定的充电位置，家或者公司都行，那么优选纯电；\n3 如果你的购车预算很充足，25万以上，那么优选纯电；\n4 如果你完全信任现有的电池技术，尤其三元锂，那么优选纯电；（这里提一下，本文对于商用乘用车电池的技术路线无歧视，但纯电车型动辄超过50-60kWh的大电池每天塞你屁股底下颠簸流离的，概率问题还是要考虑一下）\n......\n除以上条件构成的包络以外，我都是更推荐混动的。相比这些拥车、用车和养车的原则性问题，其他问题都是小问题。也列一下混动的相对优势：\n1 上下班通勤路线的距离和路况是个重要因素，如果有超过10Km的高速/快速路段，混动中发动机的介入基本被埋在风噪下了，相信现在的产品素质吧，你不会注意到发动机介入所带来的NVH问题的；\n2 再规律的充电节奏，纯电车也很难避免（突发的）极限工况需求。\n比如冬季、临时高速出短差或者游玩，或者连续社交活动不具备充电时间和条件等等。",
        "Url": "https://www.zhihu.com/question/1971486526400627517/answer/1971934241257427226?utm_medium=openapi_platform&utm_source=124a2a56",
        "CommentCount": 0,
        "VoteUpCount": 2,
        "AuthorName": "Duncan Zhang",
        "AuthorAvatar": "https://picx.zhimg.com/50/v2-4c4b892396bd0b1b79199900899eed43_l.jpg?source=bbf6831d",
        "AuthorBadge": "https://pic2.zhimg.com/v2-4a07bc69c4bb04444721f35b32125c75_l.png?source=32738c0c",
        "AuthorBadgeText": "自动驾驶等 2 个话题下的优秀答主",
        "EditTime": 1762925759,
        "AuthorityLevel": "1",
        "RankingScore": 1.5978842
      },
      {
        "Title": "中年人买家里第一辆车,无固定车位,选油车、纯电还是混动? - 知乎",
        "ContentType": "Answer",
        "ContentID": "7193613790944587728",
        "ContentText": "年里程两万四千公里以上，无脑纯电。\n年里程一万两千公里以下，无脑混动。\n年里程一万二到两万四之间，混动纯电都行，区别不大。\n反正别买纯油就对了。因为混动当纯油开，油耗只有一半不到，你买纯油的目的是什么？\n为什么里程高无脑纯电呢？因为，现实中大多数里程高的人其实对能耗都挺在意的，同时这些人一般都能接受充电开销，毕竟这点开销确实物有所值。里程高，有充电桩的应该用纯电，因为你充电方便。没充电桩的更应该用纯电，因为纯电续航长，可以减少充电次数。\n为什么里程低无脑混动呢？\n因为混动车，它电池小，所以便宜，纯电比混动贵的那部分钱，其实已经把你这辆车整个生命周期的能耗都算进去了。\n而只要你里程低，混动加油的那点费用就完全可以用混动本身便宜的车价抵消。",
        "Url": "https://www.zhihu.com/question/2015721137116558994/answer/2018046814981472525?utm_medium=openapi_platform&utm_source=124a2a56",
        "CommentCount": 38,
        "VoteUpCount": 104,
        "AuthorName": "pansz",
        "AuthorAvatar": "https://picx.zhimg.com/50/310d85e8d_l.jpg?source=bbf6831d",
        "AuthorBadge": "https://pic3.zhimg.com/v2-27bfcba90e66db79ce8768ab807e017e_l.png?source=32738c0c",
        "AuthorBadgeText": "新知答主",
        "EditTime": 1773928456,
        "CommentInfoList": [
          {
            "Content": "我就是混动，让我再选一次就干纯电"
          },
          {
            "Content": "高里程不都是刷高速刷出来的吗？纯电高速可不占优势，耗能高，补能繁琐。不如增程或者纯油。"
          },
          {
            "Content": "年里程一万两千公里以下，是无脑油车吧，你混动用纯油模式油耗是低了，但是发动机只有96匹马力，满载你爬坡都上不去，当然也有1.5T发动机的混动，但只是少数只有2，3个车企的部分车型是这种搭配，其他都是96匹马力的。"
          }
        ],
        "AuthorityLevel": "1",
        "RankingScore": 1.5878597
      },
      {
        "Title": "纯电车和插混车哪个性价比最高? - 知乎",
        "ContentType": "Answer",
        "ContentID": "-8886009937675323560",
        "ContentText": "今天回外家280公里，插混车纯电续航只剩五十多，加上有点困所以想眯一下能充电就充。虽然桩不多但但有位不用排队，而且720kw桩充个十来分钟就够了。结果插上枪扫码发现1.85一度，果断拔枪去个厕所走人，人也醒了（一半是洗脸一半是电费吓的）。上次同一个服务区充电才1.55，算了一下还是比用油划算，到1.85就没有优势了\n现在有空顺便算一下费用，我的六座SUV百公里电耗约23度，大概要充130公里续航，也就是要充30度55.5元，每公里0.43元。\n用油智能电混大概百公里8L，要用#95每公里0.6元，10.5L油费78.5差23元，每百公里只差17元，当然三百公里大多数纯电都能跑，路程远的话其实差距并不大，但会浪费一定时间成本",
        "Url": "https://www.zhihu.com/question/1994122728857428632/answer/2008361060768441238?utm_medium=openapi_platform&utm_source=124a2a56",
        "CommentCount": 14,
        "VoteUpCount": 45,
        "AuthorName": "卡曼迪全屋定制",
        "AuthorAvatar": "https://pica.zhimg.com/50/v2-aca726ec658f82e912a889db37719d50_l.jpg?source=bbf6831d",
        "AuthorBadge": "",
        "AuthorBadgeText": "",
        "EditTime": 1771836118,
        "CommentInfoList": [
          {
            "Content": "现在节假日高速上插混充电是不合算没必要[思考]基本就是1.5元以上电价就不值得费事去充电了"
          },
          {
            "Content": "我21年买的唐，出门反正就当油车开啦，不过用车体验是电车的，纯油车比不上[大笑]。加油那几分钟，你就当兆瓦闪充已经用了4年就行了。"
          },
          {
            "Content": "充电有损耗，实际上差不多1.3以上经济成本就不合适了，再考虑时间成本和快充有可能会伤电池超过一块就不要特意等了"
          }
        ],
        "AuthorityLevel": "1",
        "RankingScore": 1.570739
      },
      {
        "Title": "就现在来说,买纯油还是插混好? - 知乎",
        "ContentType": "Answer",
        "ContentID": "8030105925096898417",
        "ContentText": "本来想买纯电，家里让买纯油，疯狂商量之后家里妥协买了混动，海豹06dmi，开着是是真爽啊。\n目前公里数----11740km，()括号内为补充内容\n先说优点\n1.0-80提速比油车快，跟车蠕动比油车爽多了，油车起步总是顿几秒(cvt)\n2.午睡可以躺车里开空调，看着路边的油车打开车门，你就想买电车买值了(暖风一小时耗电大概就是一度电，冷风一小时大概在0.7度，早起送人去考试，然后找个不收停车费的充电桩，插上电，开着空调睡到考试结束，用不了五块钱）。\n3.省油(划掉)比油车百公里能省个1-2l吧\n冬天日常5-6个，你就不敢开快车，时速保持在90码以下才省油，不过我没长时间开过油车，不知道我开油车能开多少。\n夏天纯电开比油车省了一倍多。（纯烧电不跑高速能干到10度电每百公里，相当于百公里2.8l的油耗）\n4.冬天开暖风可以用发动机的热量，而且比亚迪做的很聪明，如果你想开暖风，但你刚从公司出来的那段路很堵，速度慢它又用不上发动机，发动机不发热你就用不了发动机的热量，怎么办呢，它选择直接启动发动机发电，让发动机运行在最佳工况（并非，和原地发电转速一样，应该不是热效率最高的时候），并且它消耗的油还会变成电充到电池里面，纯电的话只能用压缩机和电热丝了。\n5.不怕突然要去长途，直接开到加油站加200块钱的92就能跑大约500km，而且速度比充电快（这何尝不是闪充呢）。\n（跑多远要看油的品质，五一跑了430多公里耗了16.7l油+十度电，油是6.3元一升的时候加的，放了仨月还没烧完，电一块钱一度，加起来16.7*6.3+10=115.21，一公里不到3毛钱）",
        "Url": "https://www.zhihu.com/question/1958692581564187692/answer/1974562164091146430?utm_medium=openapi_platform&utm_source=124a2a56",
        "CommentCount": 51,
        "VoteUpCount": 81,
        "AuthorName": "思唐",
        "AuthorAvatar": "https://picx.zhimg.com/50/v2-7e7beca4b6c5388ff6af3753c636cce7_l.jpg?source=bbf6831d",
        "AuthorBadge": "",
        "AuthorBadgeText": "",
        "EditTime": 1783391009,
        "CommentInfoList": [
          {
            "Content": "同款车路过，大部分认同动力不是问题，高速上超车动力很足比较蛋疼的是底盘低，老是怕磕到电池，周末连续两天被磕到，一次是高速上有东西，一次是国道有个坎，下次换车一定得换SUV隔音差，高速超过100码，听歌体验太差，跟市区完全两个档次亏电的时候长上坡发动机声音巨大"
          },
          {
            "Content": "除了被刺的厉害，其他都好"
          },
          {
            "Content": "只要不是上高速都舍不得用油，插混就是有高速需求最完美的存在"
          }
        ],
        "AuthorityLevel": "1",
        "RankingScore": 1.5259303
      },
      {
        "Title": "中年人买家里第一辆车,无固定车位,选油车、纯电还是混动? - 知乎",
        "ContentType": "Answer",
        "ContentID": "-3910695532288241415",
        "ContentText": "中年人第一辆车，家用SUV，20以内的话，其实选择还是挺多的。要么纯电，要么油车(包含油混)，不建议混动(增程或插混)。个人更推荐油车。\n1.不选混动\n“小区无固定停车位，没有家充的条件”，无固定车位的情况下，混动会让你产生一定的焦虑，不省心。现在混动纯电续航都不算高，两百来公里，实际打折也就一百多，而且你主要还是高速，来回300公里，混动的话，如果想纯电续航肯定在外面要至少充一次电的。买了混动之后，其实心里就有了一个预期了，“我这车主要是电车，实在没办法了才是油车”，所以这个预期会让你时常陷入焦虑，纯电续航不够了，到处看充电桩。\n你或许想，买了就当纯油开。但是长时间不充电或者处于馈电状态，可能会使电池内部活性降低，加速老化，严重影响续航和性能，而且不少插混发动机是1.5T或者1.5L的，而SUV车重可能大于2吨，纯油情况体验感会下降很多。\n2.纯电\n没有自己的充电桩，其实对纯电车用车成本影响挺大的。按照年1万公里，百公里20度电算的话，每年可能要额外支出3千块钱。\n对比混动，纯电优势还是蛮大的，不过首先得买一辆续航足够大的车，按照问题的使用情况，高速续航需要大于400公里。因为没有私桩，去充电站的频次不用那么频繁，而且续航足够的话，每次出门充满电，在外面可以不用了充电了，更省心点。\n对比油车的话，电车的优势主要就是舒适性，空调自由，里程数高的话，用车成本便宜。\n辅助驾驶嘛，看个人情况了，我个人还是持比较谨慎的态度，除非哪天立法了，出了L3，出事了车企承担责任。",
        "Url": "https://www.zhihu.com/question/2015721137116558994/answer/2042589185509439068?utm_medium=openapi_platform&utm_source=124a2a56",
        "CommentCount": 1,
        "VoteUpCount": 12,
        "AuthorName": "清风入空门",
        "AuthorAvatar": "https://pic1.zhimg.com/50/v2-311a27d5ada9c174472516639ff5bbfa_l.jpg?source=bbf6831d",
        "AuthorBadge": "",
        "AuthorBadgeText": "",
        "EditTime": 1779771372,
        "CommentInfoList": [
          {
            "Content": "如果是人生第一辆车，你会选择哪种呢，我估计年级不同，选择也不同[大笑]"
          }
        ],
        "AuthorityLevel": "1",
        "RankingScore": 1.5101006
      },
      {
        "Title": "30岁,还没结婚,第一辆车,是买混动还是纯电? - 知乎",
        "ContentType": "Answer",
        "ContentID": "6240471702911067687",
        "ContentText": "首先说结论：买带纯电，优先选择闪充版本！理由如下：\n①回家里程340KM，以我的海狮07 610续航版本来说，高速120 能开390，可以保证你满电出发到家无需补能；\n②没买房就默认你没有固定车位可以安装充电桩，所以要买纯电。这可能很反直觉，即使你是混动车型，短途通勤大部分人还是用电通勤，这导致了需要更频繁的充电，如果你没有充电桩出去充电的频率会大大增加；\n③现在购买闪充版本赠送18个月免费充电权益，免费啊喂！这不狠狠的薅他一笔！至于闪充版本不送充电桩的问题，我只能说 官方7KW桩1499就能买，你如果嫌贵可以闲鱼700左右可以买到！\n④你这价位SUV我十分推荐海狮06或者宋U，记住一定要买闪充版！\n唯一的缺点就是要等车！",
        "Url": "https://www.zhihu.com/question/2051984422581360622/answer/2056329703250825845?utm_medium=openapi_platform&utm_source=124a2a56",
        "CommentCount": 0,
        "VoteUpCount": 1,
        "AuthorName": "张近东",
        "AuthorAvatar": "https://picx.zhimg.com/50/v2-b9f0c55837771e4154c5b2189bb990e8_l.jpg?source=bbf6831d",
        "AuthorBadge": "",
        "AuthorBadgeText": "",
        "EditTime": 1783047206,
        "AuthorityLevel": "1",
        "RankingScore": 1.4951919
      },
      {
        "Title": "丰田的油混系统为什么不把电池做大点? - 知乎",
        "ContentType": "Answer",
        "ContentID": "3703254556333312738",
        "ContentText": "一句话，如果这台车是全球车型，大电池带来的优点远远少于缺点和风险。\n丰田的双擎是适合全球车型，也就是说适合地球所有国度。\n从设计之初，那个小电池就是为了解决燃油发动机低速情况下效率低下的问题，降低油耗，电池只浅充浅放，使用寿命长，成本低，无自燃风险。\n电池为什么不做大？国外很多地方油价和电价差距不大，比如美国，油价1.1美元/升，电价0.3-0.4美元/度。算下来燃油车和纯电车使用成本基乎相当。那增大电池容量没有经济实用性，又占用空间体积，又增加车身重量，又增加自燃风险，又增加日后更换成本，收益远低于缺点，有什么意义呢？\n国内现在主推的纯电、插混、增程，你觉得使用成本低是因为油价太高，电便宜，油价7-8元人民币/升，电价0.6元人民币/度，所以很多人买了插混或增程，纯电行驶里程占大头，相对于烧油成本显得便宜，这才是根本原本原因。",
        "Url": "https://www.zhihu.com/question/1909394428658943229/answer/1909955351782069228?utm_medium=openapi_platform&utm_source=124a2a56",
        "CommentCount": 477,
        "VoteUpCount": 770,
        "AuthorName": "小李探花",
        "AuthorAvatar": "https://pic1.zhimg.com/50/v2-9a3d29fdad42dde990ebf893f972d584_l.jpg?source=bbf6831d",
        "AuthorBadge": "",
        "AuthorBadgeText": "",
        "EditTime": 1780803514,
        "CommentInfoList": [
          {
            "Content": "还在宣扬这套说法，按你这个逻辑丰田应该早就在国内推出插混车型了，不至于现在这样节节败退"
          },
          {
            "Content": "是的。在外国很多地区，开电车才是想不开呢[捂脸]，中国也不是适合所有地区的。"
          },
          {
            "Content": "那请问为什么丰田全面转用三元锂电池了？为什么rav4插混版卖5万美元还加价，等车周期超过一年结果还被疯抢？丰田自己电池越做越大，混动逻辑越来越倾向于大功率充放电，你应该就能看出来是什么趋势。"
          }
        ],
        "AuthorityLevel": "1",
        "RankingScore": 1.4950681
      }
    ]
  },
  "_query": "混动还是纯电怎么选"
}
